pluma/__init__.py
pluma/_version.py
pluma/export/maps.py
pluma/export/streams.py
pluma/export/ogcapi/features.py
pluma/export/ogcapi/records.py
pluma/io/accelerometer.py
pluma/io/eeg.py
pluma/io/empatica.py
pluma/io/harp.py
pluma/io/microphone.py
pluma/io/path_helper.py
pluma/io/ubx.py
pluma/io/zeromq.py
pluma/preprocessing/ecg.py
pluma/preprocessing/resampling.py
pluma/preprocessing/utils.py
pluma/schema/__init__.py
pluma/schema/outdoor.py
pluma/schema/vr.py
pluma/stream/__init__.py
pluma/stream/accelerometer.py
pluma/stream/csv.py
pluma/stream/ecg.py
pluma/stream/eeg.py
pluma/stream/empatica.py
pluma/stream/georeference.py
pluma/stream/glia.py
pluma/stream/harp.py
pluma/stream/microphone.py
pluma/stream/pupil.py
pluma/stream/siconversion.py
pluma/stream/ubx.py
pluma/stream/unity.py
pluma/stream/zeromq.py
pluma/sync/__init__.py
pluma/sync/plotting.py
pluma/sync/ubx2harp.py
pluma/templates/metadata_template.j2
pluma_analysis-0.10.0.dist-info/LICENSE
pluma_analysis-0.10.0.dist-info/METADATA
pluma_analysis-0.10.0.dist-info/WHEEL
pluma_analysis-0.10.0.dist-info/top_level.txt
pluma_analysis-0.10.0.dist-info/RECORD
