Metadata-Version: 2.2
Name: pluma-analysis
Version: 0.10.0
Summary: A low-level interface to data collected with the pluma urban data acquisition system
Author-email: Goncalo Lopes <g.lopes@neurogears.org>, Bruno Cruz <b.cruz@neurogears.org>, Andrew Erskine <a.erskine@neurogears.org>
License: MIT License
Project-URL: Bug Tracker, https://github.com/emotional-cities/pluma-analysis/issues
Project-URL: Source Code, https://github.com/emotional-cities/pluma-analysis
Classifier: Development Status :: 4 - Beta
Classifier: Programming Language :: Python
Classifier: Programming Language :: Python :: 3
Classifier: Programming Language :: Python :: 3.9
Classifier: Programming Language :: Python :: 3.10
Classifier: Operating System :: OS Independent
Classifier: License :: OSI Approved :: MIT License
Requires-Python: >=3.9.0
License-File: LICENSE
Requires-Dist: geopandas
Requires-Dist: matplotlib
Requires-Dist: mapclassify
Requires-Dist: folium
Requires-Dist: numpy
Requires-Dist: scipy
Requires-Dist: scikit-learn
Requires-Dist: pandas
Requires-Dist: s3fs
Requires-Dist: pyubx2
Requires-Dist: tilemapbase
Requires-Dist: dotmap
Requires-Dist: mne
Requires-Dist: defusedxml
Requires-Dist: heartpy
Requires-Dist: setuptools
Requires-Dist: simplekml
Requires-Dist: isodate
Requires-Dist: jinja2
Provides-Extra: dev
Requires-Dist: ruff; extra == "dev"
